ai_university_bio/__init__.py
ai_university_bio/lab.py
ai_university_bio-1.1.4.dist-info/METADATA
ai_university_bio-1.1.4.dist-info/WHEEL
ai_university_bio-1.1.4.dist-info/top_level.txt
ai_university_bio-1.1.4.dist-info/RECORD
