Metadata-Version: 2.1
Name: ai-university-bio
Version: 1.1.4
Summary: Genetics model
Home-page: UNKNOWN
Author: AI University
Author-email: nejronki@gmail.compile
License: UNKNOWN
Platform: UNKNOWN
Classifier: Programming Language :: Python :: 3
Classifier: License :: OSI Approved :: MIT License
Classifier: Operating System :: OS Independent
Requires-Python: >=3.6
